configure_django.py
version.py
configure_django/__init__.py
configure_django/configure_django.py
configure_django-0.3.6.dist-info/AUTHORS.md
configure_django-0.3.6.dist-info/LICENSE
configure_django-0.3.6.dist-info/METADATA
configure_django-0.3.6.dist-info/WHEEL
configure_django-0.3.6.dist-info/top_level.txt
configure_django-0.3.6.dist-info/RECORD
