Metadata-Version: 2.1
Name: configure-django
Version: 0.3.6
Summary: A package for configuring Django in non-traditional environments.
Home-page: https://github.com/pydanny/configure_django
Author: Daniel Roy Greenfeld
Author-email: pydanny@gmail.com
License: Apache Software License 2.0
Keywords: configure_django
Platform: UNKNOWN
Classifier: Development Status :: 2 - Pre-Alpha
Classifier: Intended Audience :: Developers
Classifier: License :: OSI Approved :: Apache Software License
Classifier: Natural Language :: English
Classifier: Framework :: Django
Classifier: Framework :: Django :: 2.1
Classifier: Programming Language :: Python :: 3
Classifier: Programming Language :: Python :: 3.6
Classifier: Programming Language :: Python :: 3.7
Requires-Dist: dj-database-url
Requires-Dist: python-decouple
Requires-Dist: django
